LICENSE
MANIFEST.in
README.txt
pybtctool
setup.cfg
setup.py
bitcoin/__init__.py
bitcoin/bci.py
bitcoin/blocks.py
bitcoin/composite.py
bitcoin/deterministic.py
bitcoin/main.py
bitcoin/ripemd.py
bitcoin/stealth.py
bitcoin/transaction.py
digibyte.egg-info/PKG-INFO
digibyte.egg-info/SOURCES.txt
digibyte.egg-info/dependency_links.txt
digibyte.egg-info/requires.txt
digibyte.egg-info/top_level.txt