Metadata-Version: 1.0
Name: digibyte
Version: 1.1.25
Summary: Python Digibyte Tools
Home-page: http://github.com/Digitools/pydigibytetools
Author: Esotericizm
Author-email: esotericizm@cryptoservices.net
License: UNKNOWN
Platform: UNKNOWN
